LICENSE
NOTICE
README.md
setup.cfg
setup.py
fbs/__init__.py
fbs/__main__.py
fbs/_state.py
fbs/cmdline.py
fbs/resources.py
fbs/_defaults/src/build/settings/arch.json
fbs/_defaults/src/build/settings/base.json
fbs/_defaults/src/build/settings/fedora.json
fbs/_defaults/src/build/settings/linux.json
fbs/_defaults/src/build/settings/mac.json
fbs/_defaults/src/build/settings/ubuntu.json
fbs/_defaults/src/build/settings/windows.json
fbs/_defaults/src/installer/linux/usr/share/applications/AppName.desktop
fbs/_defaults/src/installer/windows/Installer.nsi
fbs/_defaults/src/installer/windows/ShellExecAsUser.dll
fbs/builtin_commands/__init__.py
fbs/builtin_commands/_util.py
fbs/builtin_commands/project_template/src/build/settings/base.json
fbs/builtin_commands/project_template/src/build/settings/linux.json
fbs/builtin_commands/project_template/src/build/settings/mac.json
fbs/builtin_commands/project_template/src/main/icons/Icon.ico
fbs/builtin_commands/project_template/src/main/icons/README.md
fbs/builtin_commands/project_template/src/main/icons/base/16.png
fbs/builtin_commands/project_template/src/main/icons/base/24.png
fbs/builtin_commands/project_template/src/main/icons/base/32.png
fbs/builtin_commands/project_template/src/main/icons/base/48.png
fbs/builtin_commands/project_template/src/main/icons/base/64.png
fbs/builtin_commands/project_template/src/main/icons/linux/1024.png
fbs/builtin_commands/project_template/src/main/icons/linux/128.png
fbs/builtin_commands/project_template/src/main/icons/linux/256.png
fbs/builtin_commands/project_template/src/main/icons/linux/512.png
fbs/builtin_commands/project_template/src/main/icons/mac/1024.png
fbs/builtin_commands/project_template/src/main/icons/mac/128.png
fbs/builtin_commands/project_template/src/main/icons/mac/256.png
fbs/builtin_commands/project_template/src/main/icons/mac/512.png
fbs/builtin_commands/project_template/src/main/python/main.py
fbs/installer/__init__.py
fbs/installer/arch.py
fbs/installer/fedora.py
fbs_tutorial_shim.egg-info/PKG-INFO
fbs_tutorial_shim.egg-info/SOURCES.txt
fbs_tutorial_shim.egg-info/dependency_links.txt
fbs_tutorial_shim.egg-info/entry_points.txt
fbs_tutorial_shim.egg-info/requires.txt
fbs_tutorial_shim.egg-info/top_level.txt