Metadata-Version: 2.1
Name: fbs-tutorial-shim
Version: 1.0.1
Summary: fbs tutorial helper
Home-page: https://github.com/mherrmann/fbs-tutorial-shim
Author: Michael Herrmann
Author-email: michael+removethisifyouarehuman@herrmann.io
License: GPLv3 or later
Keywords: PyQt
Platform: MacOS
Platform: Windows
Classifier: Development Status :: 4 - Beta
Classifier: Intended Audience :: Developers
Classifier: License :: OSI Approved :: GNU General Public License v3 or later (GPLv3+)
Classifier: Operating System :: OS Independent
Classifier: Programming Language :: Python
Classifier: Programming Language :: Python :: 3
Classifier: Programming Language :: Python :: 3.7
Classifier: Programming Language :: Python :: 3.8
Classifier: Programming Language :: Python :: 3.9
Classifier: Topic :: Software Development :: Libraries
Classifier: Topic :: Software Development :: Libraries :: Python Modules
License-File: LICENSE
License-File: NOTICE
